.gitattributes
.gitignore
.pre-commit-config.yaml
.readthedocs-custom-steps.yml
.readthedocs-requirements.txt
.readthedocs.yml
.travis.yml
LICENSE
MANIFEST.in
README.md
changelog.md
create_env.sh
pydoc-markdown.yml
pyproject.toml
setup.py
training.md
update_version.py
.github/dependabot.yml
.github/workflows/ipynb.yml
.github/workflows/python.yml
.github/workflows/upload_pypi.yml
docs/start.md
generate_training_data/clean.py
generate_training_data/generate_FC_data.py
generate_training_data/generate_data.py
generate_training_data/generate_metadata.py
generate_training_data/inputresonantparams.csv
generate_training_data/reproducibility.ipynb
generate_training_data/test_features.ipynb
generate_training_data/test_features.py
generate_training_data/training_data_functions.py
jupyter_examples/ComparingToNbody.ipynb
jupyter_examples/GiantImpactPhase.ipynb
jupyter_examples/GridOfStabilityPredictions.ipynb
jupyter_examples/HowToCite.ipynb
jupyter_examples/QuickStart.ipynb
jupyter_examples/ipynb2py.py
paper_plots/US_background_image.png
paper_plots/cleanVnonClean.ipynb
paper_plots/compareTsec.ipynb
paper_plots/error.ipynb
paper_plots/fig2.ipynb
paper_plots/fig3.ipynb
paper_plots/fig4.ipynb
paper_plots/fig5.ipynb
paper_plots/fig6.ipynb
paper_plots/fig7.ipynb
paper_plots/fig8.ipynb
paper_plots/generatePratios.py
paper_plots/oldReboundNewRebound.ipynb
paper_plots/paper.mplstyle
paper_plots/pr.ipynb
paper_plots/prseeds.txt
paper_plots/sa0000000.bin
paper_plots/spockpr.jpg
paper_plots/testUnstable.ipynb
paper_plots/alysa-datafiles/initial_conditions_delta_10_to_13.npz
paper_plots/alysa-datafiles/initial_conditions_delta_2_to_10.npz
paper_plots/alysa-datafiles/merged_output_files_delta_10_to_13.npz
paper_plots/alysa-datafiles/merged_output_files_delta_2_to_10.npz
paper_plots/alysa-datafiles/spockprobs.npz
run_integrations/README.txt
run_integrations/gen_whfastcomparison_commands.txt
run_integrations/inputresonantparams.csv
run_integrations/runcomparison.py
spock.egg-info/PKG-INFO
spock.egg-info/SOURCES.txt
spock.egg-info/dependency_links.txt
spock.egg-info/not-zip-safe
spock.egg-info/requires.txt
spock.egg-info/top_level.txt
