Metadata-Version: 2.4
Name: spock
Version: 2.1.1
Summary: Stability of Planetary Orbital Configurations Klassifier
Author-email: Daniel Tamayo <tamayo.daniel@gmail.com>, Miles Cranmer <miles.cranmer@gmail.com>, Hanno Rein <hanno@hanno-rein.de>, Caleb Lammers <cl5968@princeton.edu>, Elio Thadhani <ethadhani@hmc.edu>, Yolanda Ba <yba@hmc.edu>
License:                     GNU GENERAL PUBLIC LICENSE
Project-URL: Homepage, https://github.com/dtamayo/spock
Keywords: astronomy,astrophysics,exoplanets,stability
Classifier: Development Status :: 3 - Alpha
Classifier: Intended Audience :: Science/Research
Classifier: Intended Audience :: Developers
Classifier: Topic :: Software Development :: Build Tools
Classifier: Topic :: Scientific/Engineering :: Astronomy
Classifier: License :: OSI Approved :: GNU General Public License v3 or later (GPLv3+)
Classifier: Programming Language :: Python :: 3
Requires-Python: >=3.9
License-File: LICENSE
Requires-Dist: rebound<5.0.0,>=4.0.1
Requires-Dist: scikit-learn<1.6.0
Requires-Dist: xgboost<3.0.0,>=1.1.0
Requires-Dist: torch<3.0.0,>=1.5.1
Requires-Dist: safetensors<0.5.0,>=0.4.0
Requires-Dist: scipy<2.0.0
Requires-Dist: einops<0.9.0
Requires-Dist: numpy<3.0.0
Requires-Dist: celmech<1.6.0,>=1.5.0
Provides-Extra: test
Requires-Dist: IPython; extra == "test"
Requires-Dist: matplotlib; extra == "test"
Requires-Dist: pandas; extra == "test"
Requires-Dist: jupyter; extra == "test"
Dynamic: license-file
